pandoras/__init__.py
pandoras/pandoras.py
pandoras-0.1.1.dist-info/LICENSE
pandoras-0.1.1.dist-info/METADATA
pandoras-0.1.1.dist-info/WHEEL
pandoras-0.1.1.dist-info/RECORD
