Metadata-Version: 2.3
Name: pandoras
Version: 0.1.1
Summary: Undo/Redo functionality for Pandas DataFrames using Apache Arrow
License: MIT
Author: al2m4n
Author-email: al2m4n@gmail.com
Requires-Python: >=3.13
Classifier: License :: OSI Approved :: MIT License
Classifier: Programming Language :: Python :: 3
Classifier: Programming Language :: Python :: 3.13
Requires-Dist: pandas (>=2.2.3,<3.0.0)
Requires-Dist: pyarrow (>=19.0.1,<20.0.0)
